autograph/__init__.py
autograph/core/__init__.py
autograph/core/enumstyle.py
autograph/core/plot.py
autograph/core/style.py
autograph/wrapper/__init__.py
autograph/wrapper/mpl.py
autograph/wrapper/plotly.py
crillab_autograph-0.1.0.dist-info/METADATA
crillab_autograph-0.1.0.dist-info/WHEEL
crillab_autograph-0.1.0.dist-info/licenses/LICENSE.md
crillab_autograph-0.1.0.dist-info/RECORD
