Metadata-Version: 2.1
Name: crillab-autograph
Version: 0.1.0
Summary: AUtogRAPH - A Unified libRary for drAwing Plots in pytHon
Keywords: visualization plots
Author: Thibault Falque, Romain Wallon, Hugues Wattez
Author-Email: Unknown <metrics@cril.fr>
License: MIT
Classifier: Development Status :: 4 - Beta
Classifier: License :: OSI Approved :: MIT License
Classifier: Operating System :: OS Independent
Classifier: Programming Language :: Python :: 3.8
Project-URL: Homepage, https://github.com/crillab/autograph
Requires-Python: >=3.10
Requires-Dist: Cython
Requires-Dist: Pillow
Requires-Dist: cycler
Requires-Dist: kiwisolver
Requires-Dist: matplotlib
Requires-Dist: nose
Requires-Dist: numpy
Requires-Dist: pip
Requires-Dist: plotly
Requires-Dist: pyparsing
Requires-Dist: python-dateutil
Requires-Dist: retrying
Requires-Dist: seaborn
Requires-Dist: setuptools
Requires-Dist: six
